backstage_catalog_client/__init__.py
backstage_catalog_client/catalog_api/__init__.py
backstage_catalog_client/catalog_api/async_api.py
backstage_catalog_client/catalog_api/sync_api.py
backstage_catalog_client/catalog_api/util.py
backstage_catalog_client/entity.py
backstage_catalog_client/httpx_client.py
backstage_catalog_client/models.py
backstage_catalog_client/py.typed
backstage_catalog_client/utils.py
backstage_catalog_client-0.1.0.dist-info/LICENSE
backstage_catalog_client-0.1.0.dist-info/METADATA
backstage_catalog_client-0.1.0.dist-info/WHEEL
backstage_catalog_client-0.1.0.dist-info/RECORD
