Metadata-Version: 2.1
Name: backstage_catalog_client
Version: 0.1.0
Summary: a python client for the Backstage catalog API
Home-page: https://github.com/mspiegel31/backstage-catalog-client
Author: Mike Spiegel
Author-email: mspiegel31@gmail.com
Requires-Python: >=3.8,<4.0
Classifier: Programming Language :: Python :: 3
Classifier: Programming Language :: Python :: 3.8
Classifier: Programming Language :: Python :: 3.9
Classifier: Programming Language :: Python :: 3.10
Classifier: Programming Language :: Python :: 3.11
Classifier: Programming Language :: Python :: 3.12
Requires-Dist: httpx (>=0.27.0,<0.28.0)
Requires-Dist: typing-extensions (>=4.10.0,<5.0.0)
Requires-Dist: uritemplate (>=4.1.1,<5.0.0)
Project-URL: Documentation, https://mspiegel31.github.io/backstage-catalog-client/
Project-URL: Repository, https://github.com/mspiegel31/backstage-catalog-client
